solr_conabio/__init__.py
solr_conabio/__version__.py
solr_conabio/solr_api.py
solr_conabio-0.2.dist-info/METADATA
solr_conabio-0.2.dist-info/RECORD
solr_conabio-0.2.dist-info/WHEEL
solr_conabio-0.2.dist-info/top_level.txt
